datasette_debug_asgi.py
datasette_debug_asgi-1.1.dist-info/LICENSE
datasette_debug_asgi-1.1.dist-info/METADATA
datasette_debug_asgi-1.1.dist-info/WHEEL
datasette_debug_asgi-1.1.dist-info/entry_points.txt
datasette_debug_asgi-1.1.dist-info/top_level.txt
datasette_debug_asgi-1.1.dist-info/RECORD
