Metadata-Version: 2.1
Name: datasette-debug-asgi
Version: 1.1
Summary: Datasette plugin for dumping out the ASGI scope
Home-page: https://github.com/simonw/datasette-debug-asgi
Author: Simon Willison
License: Apache License, Version 2.0
Project-URL: Issues, https://github.com/simonw/datasette-debug-asgi/issues
Project-URL: CI, https://github.com/simonw/datasette-debug-asgi/actions
Project-URL: Changelog, https://github.com/simonw/datasette-debug-asgi/releases
Platform: UNKNOWN
Requires-Python: >=3.6
Requires-Dist: datasette (>=0.50)
Provides-Extra: test
Requires-Dist: pytest ; extra == 'test'
Requires-Dist: pytest-asyncio ; extra == 'test'
